quickresize/__init__.py
quickresize/centercrop.py
quickresize/resize.py
quickresize-0.4.0.dist-info/LICENSE
quickresize-0.4.0.dist-info/METADATA
quickresize-0.4.0.dist-info/WHEEL
quickresize-0.4.0.dist-info/entry_points.txt
quickresize-0.4.0.dist-info/top_level.txt
quickresize-0.4.0.dist-info/RECORD
