Metadata-Version: 2.1
Name: quickresize
Version: 0.4.0
Summary: In-place resizing and center-crop of images present in a folder
Author: Nityanand Mathur
License: MIT
License-File: LICENSE
Requires-Dist: tqdm
Requires-Dist: pillow
